Metadata-Version: 2.4
Name: x_4357_make_pip_updates_x
Version: 0.20.17
Summary: Makes pip package updates.
Author-email: "RRGM (Software Tech Lead, Primus Pilus Night Watch AI Corp.)" <foo@bar.com>
Requires-Python: >=3.8
